{
    "a_diodes": 16,
    "column": "1",
    "delay_fbias": 1,
    "delay_rbias": 1,
    "die_nr": "28",
    "diode_Nr": "3,2",
    "entrance_window": "E",
    "guardring_value": "15",
    "identifier": "04E15",
    "iv_data_fbias": [
        [
            0.0,
            5.969588e-13
        ],
        [
            -0.2,
            -2.843764e-11
        ],
        [
            -0.4,
            -4.420968e-08
        ],
        [
            -0.6,
            -1.561242e-06
        ],
        [
            -0.8,
            -6.147073e-06
        ],
        [
            -1.0,
            -1.889246e-05
        ],
        [
            -1.2,
            -4.610988e-05
        ],
        [
            -1.4,
            -9.296196e-05
        ],
        [
            -1.6,
            -0.0001655448
        ],
        [
            -1.8,
            -0.0002693831
        ],
        [
            -2.0,
            -0.0004098335
        ],
        [
            -2.2,
            -0.0005900146
        ],
        [
            -2.4,
            -0.0008156707
        ],
        [
            -2.6,
            -0.001089325
        ],
        [
            -2.8,
            -0.001410805
        ],
        [
            -3.0,
            -0.001783017
        ],
        [
            -3.2,
            -0.002210374
        ]
    ],
    "iv_data_rbias": [
        [
            0.0,
            1.436995e-13
        ],
        [
            0.5,
            -6.311436e-15
        ],
        [
            1.0,
            4.45809e-14
        ],
        [
            1.5,
            1.628468e-15
        ],
        [
            2.0,
            4.091738e-14
        ],
        [
            2.5,
            5.923499e-14
        ],
        [
            3.0,
            -2.036108e-15
        ],
        [
            3.5,
            3.643974e-14
        ],
        [
            4.0,
            1.180781e-14
        ],
        [
            4.5,
            1.730466e-14
        ],
        [
            5.0,
            9.464905e-14
        ],
        [
            5.5,
            2.422661e-14
        ],
        [
            6.0,
            1.62846e-15
        ],
        [
            6.5,
            -2.850456e-15
        ],
        [
            7.0,
            3.033387e-14
        ],
        [
            7.5,
            4.824443e-14
        ],
        [
            8.0,
            2.707682e-14
        ],
        [
            8.5,
            6.921714e-15
        ],
        [
            9.0,
            3.623621e-14
        ],
        [
            9.5,
            3.481151e-14
        ],
        [
            10.0,
            3.359033e-14
        ],
        [
            10.5,
            6.900439e-14
        ],
        [
            11.0,
            9.771931e-15
        ],
        [
            11.5,
            1.689748e-14
        ],
        [
            12.0,
            7.653498e-14
        ],
        [
            12.5,
            3.420092e-14
        ],
        [
            13.0,
            4.905855e-14
        ],
        [
            13.5,
            6.880087e-14
        ],
        [
            14.0,
            5.597853e-14
        ],
        [
            14.5,
            -8.145814e-16
        ],
        [
            15.0,
            4.254561e-14
        ],
        [
            15.5,
            -2.443277e-15
        ],
        [
            16.0,
            2.646606e-14
        ],
        [
            16.5,
            7.205732e-14
        ],
        [
            17.0,
            2.931622e-14
        ],
        [
            17.5,
            7.877379e-14
        ],
        [
            18.0,
            2.809476e-14
        ],
        [
            18.5,
            1.486161e-14
        ],
        [
            19.0,
            5.923499e-14
        ],
        [
            19.5,
            8.874672e-14
        ],
        [
            20.0,
            2.524454e-14
        ],
        [
            20.5,
            8.284438e-14
        ],
        [
            21.0,
            5.943853e-14
        ],
        [
            21.5,
            5.272206e-14
        ],
        [
            22.0,
            -8.754462e-15
        ],
        [
            22.5,
            1.425085e-14
        ],
        [
            23.0,
            8.854319e-14
        ],
        [
            23.5,
            1.11542e-13
        ],
        [
            24.0,
            9.444553e-14
        ],
        [
            24.5,
            8.610083e-14
        ],
        [
            25.0,
            6.513735e-14
        ],
        [
            25.5,
            9.790552e-14
        ],
        [
            26.0,
            1.740254e-13
        ],
        [
            26.5,
            1.266031e-13
        ],
        [
            27.0,
            1.182584e-13
        ],
        [
            27.5,
            1.243643e-13
        ],
        [
            28.0,
            1.813525e-13
        ],
        [
            28.5,
            1.457349e-13
        ],
        [
            29.0,
            1.272137e-13
        ],
        [
            29.5,
            1.003478e-13
        ],
        [
            30.0,
            1.544866e-13
        ],
        [
            30.5,
            1.485843e-13
        ],
        [
            31.0,
            2.021125e-13
        ],
        [
            31.5,
            1.909183e-13
        ],
        [
            32.0,
            1.817595e-13
        ],
        [
            32.5,
            1.111349e-13
        ],
        [
            33.0,
            2.106606e-13
        ],
        [
            33.5,
            2.232794e-13
        ],
        [
            34.0,
            1.715831e-13
        ],
        [
            34.5,
            2.344735e-13
        ],
        [
            35.0,
            2.3081e-13
        ],
        [
            35.5,
            2.497382e-13
        ],
        [
            36.0,
            2.951252e-13
        ],
        [
            36.5,
            2.495347e-13
        ],
        [
            37.0,
            3.189381e-13
        ],
        [
            37.5,
            2.395618e-13
        ],
        [
            38.0,
            2.536052e-13
        ],
        [
            38.5,
            2.544194e-13
        ],
        [
            39.0,
            2.79657e-13
        ],
        [
            39.5,
            2.83117e-13
        ],
        [
            40.0,
            3.236192e-13
        ],
        [
            40.5,
            3.132392e-13
        ],
        [
            41.0,
            3.468216e-13
        ],
        [
            41.5,
            3.685992e-13
        ],
        [
            42.0,
            4.101191e-13
        ],
        [
            42.5,
            5.3244e-13
        ],
        [
            43.0,
            8.222655e-13
        ],
        [
            43.5,
            5.198752e-12
        ],
        [
            44.0,
            1.743105e-10
        ],
        [
            44.5,
            5.500188e-06
        ],
        [
            45.0,
            1.426723e-05
        ],
        [
            45.5,
            2.708085e-05
        ],
        [
            46.0,
            6.241916e-05
        ],
        [
            46.5,
            8.444078e-05
        ],
        [
            47.0,
            0.0001022209
        ],
        [
            47.5,
            0.0001218805
        ],
        [
            48.0,
            0.0001429345
        ],
        [
            48.5,
            0.0001639543
        ],
        [
            49.0,
            0.0001852838
        ],
        [
            49.5,
            0.0002081138
        ],
        [
            50.0,
            0.0002273099
        ]
    ],
    "row": "-4",
    "start_fbias": 0,
    "start_rbias": 0,
    "step_fbias": 0.2,
    "step_rbias": 0.5,
    "stop_fbias": -3.5,
    "stop_rbias": 50,
    "subdie_nr": "6",
    "temp_at_end": 25.0,
    "temp_at_start": 25.0,
    "time_at_end": "2025_06_16-06_32_56",
    "time_at_start": "2025_06_16-06_30_12",
    "x_pos": "-30001.60104",
    "y_pos": "127208.01705"
}