{
    "a_diodes": 4,
    "column": "0",
    "delay_fbias": 1,
    "delay_rbias": 1,
    "die_nr": "3",
    "diode_Nr": "2,2",
    "entrance_window": "E",
    "guardring_value": "20",
    "identifier": "02E20",
    "iv_data_fbias": [
        [
            0.0,
            6.116116e-13
        ],
        [
            -0.2,
            -3.005975e-11
        ],
        [
            -0.4,
            -4.712292e-08
        ],
        [
            -0.6,
            -1.651644e-06
        ],
        [
            -0.8,
            -6.640701e-06
        ],
        [
            -1.0,
            -1.978855e-05
        ],
        [
            -1.2,
            -4.739772e-05
        ],
        [
            -1.4,
            -9.496901e-05
        ],
        [
            -1.6,
            -0.0001682587
        ],
        [
            -1.8,
            -0.0002732287
        ],
        [
            -2.0,
            -0.0004158329
        ],
        [
            -2.2,
            -0.0006017127
        ],
        [
            -2.4,
            -0.0008317953
        ],
        [
            -2.6,
            -0.001111965
        ],
        [
            -2.8,
            -0.001444071
        ],
        [
            -3.0,
            -0.001828509
        ],
        [
            -3.2,
            -0.002278455
        ]
    ],
    "iv_data_rbias": [
        [
            0.0,
            2.789118e-14
        ],
        [
            0.5,
            -1.60835e-14
        ],
        [
            1.0,
            -3.053974e-15
        ],
        [
            1.5,
            1.221501e-14
        ],
        [
            2.0,
            2.03569e-15
        ],
        [
            2.5,
            -2.38198e-14
        ],
        [
            3.0,
            3.297974e-14
        ],
        [
            3.5,
            -5.497017e-15
        ],
        [
            4.0,
            7.348194e-14
        ],
        [
            4.5,
            3.379385e-14
        ],
        [
            5.0,
            5.435025e-14
        ],
        [
            5.5,
            2.239271e-15
        ],
        [
            6.0,
            -1.099385e-14
        ],
        [
            6.5,
            -2.443226e-15
        ],
        [
            7.0,
            4.926203e-14
        ],
        [
            7.5,
            -2.972381e-14
        ],
        [
            8.0,
            3.827148e-14
        ],
        [
            8.5,
            3.216563e-14
        ],
        [
            9.0,
            4.844792e-14
        ],
        [
            9.5,
            4.030677e-14
        ],
        [
            10.0,
            2.768759e-14
        ],
        [
            10.5,
            5.862436e-14
        ],
        [
            11.0,
            8.264074e-14
        ],
        [
            11.5,
            3.460797e-14
        ],
        [
            12.0,
            5.272202e-14
        ],
        [
            12.5,
            4.132442e-14
        ],
        [
            13.0,
            4.33597e-14
        ],
        [
            13.5,
            4.743027e-14
        ],
        [
            14.0,
            1.140067e-14
        ],
        [
            14.5,
            -1.140102e-14
        ],
        [
            15.0,
            4.702322e-14
        ],
        [
            15.5,
            7.226077e-14
        ],
        [
            16.0,
            -1.506557e-14
        ],
        [
            16.5,
            1.302936e-14
        ],
        [
            17.0,
            1.384371e-14
        ],
        [
            17.5,
            3.277621e-14
        ],
        [
            18.0,
            5.293072e-15
        ],
        [
            18.5,
            5.862436e-14
        ],
        [
            19.0,
            2.60589e-14
        ],
        [
            19.5,
            6.208433e-14
        ],
        [
            20.0,
            7.409253e-14
        ],
        [
            20.5,
            1.669392e-14
        ],
        [
            21.0,
            1.123559e-13
        ],
        [
            21.5,
            7.755251e-14
        ],
        [
            22.0,
            9.1596e-14
        ],
        [
            22.5,
            7.775603e-14
        ],
        [
            23.0,
            8.732189e-14
        ],
        [
            23.5,
            6.920784e-14
        ],
        [
            24.0,
            4.62091e-14
        ],
        [
            24.5,
            1.025866e-13
        ],
        [
            25.0,
            5.109379e-14
        ],
        [
            25.5,
            7.958781e-14
        ],
        [
            26.0,
            7.795958e-14
        ],
        [
            26.5,
            7.429606e-14
        ],
        [
            27.0,
            4.519146e-14
        ],
        [
            27.5,
            1.119489e-13
        ],
        [
            28.0,
            1.278241e-13
        ],
        [
            28.5,
            6.493374e-14
        ],
        [
            29.0,
            1.591675e-13
        ],
        [
            29.5,
            1.015689e-13
        ],
        [
            30.0,
            1.213112e-13
        ],
        [
            30.5,
            1.135771e-13
        ],
        [
            31.0,
            1.003477e-13
        ],
        [
            31.5,
            5.943846e-14
        ],
        [
            32.0,
            1.188688e-13
        ],
        [
            32.5,
            9.363127e-14
        ],
        [
            33.0,
            1.147982e-13
        ],
        [
            33.5,
            1.172406e-13
        ],
        [
            34.0,
            1.471593e-13
        ],
        [
            34.5,
            1.066571e-13
        ],
        [
            35.0,
            1.298594e-13
        ],
        [
            35.5,
            1.689369e-13
        ],
        [
            36.0,
            1.345405e-13
        ],
        [
            36.5,
            1.398323e-13
        ],
        [
            37.0,
            1.876615e-13
        ],
        [
            37.5,
            1.55504e-13
        ],
        [
            38.0,
            2.027226e-13
        ],
        [
            38.5,
            2.228719e-13
        ],
        [
            39.0,
            1.707686e-13
        ],
        [
            39.5,
            2.155449e-13
        ],
        [
            40.0,
            2.865764e-13
        ],
        [
            40.5,
            2.436318e-13
        ],
        [
            41.0,
            2.454636e-13
        ],
        [
            41.5,
            3.107963e-13
        ],
        [
            42.0,
            3.492633e-13
        ],
        [
            42.5,
            4.432934e-13
        ],
        [
            43.0,
            6.641219e-13
        ],
        [
            43.5,
            6.190532e-12
        ],
        [
            44.0,
            1.857456e-10
        ],
        [
            44.5,
            5.931819e-06
        ],
        [
            45.0,
            1.650008e-05
        ],
        [
            45.5,
            3.310621e-05
        ],
        [
            46.0,
            6.164399e-05
        ],
        [
            46.5,
            8.382265e-05
        ],
        [
            47.0,
            0.000103163
        ],
        [
            47.5,
            0.0001234593
        ],
        [
            48.0,
            0.0001438487
        ],
        [
            48.5,
            0.0001653649
        ],
        [
            49.0,
            0.0001860481
        ],
        [
            49.5,
            0.0002096128
        ],
        [
            50.0,
            0.000230879
        ]
    ],
    "row": "9",
    "start_fbias": 0,
    "start_rbias": 0,
    "step_fbias": 0.2,
    "step_rbias": 0.5,
    "stop_fbias": -3.5,
    "stop_rbias": 50,
    "subdie_nr": "10",
    "temp_at_end": 25.0,
    "temp_at_start": 25.0,
    "time_at_end": "2025_06_06-15_56_12",
    "time_at_start": "2025_06_06-15_53_27",
    "x_pos": "-20401.06736",
    "y_pos": "19201.06894"
}