{
    "a_diodes": 1,
    "column": "-2",
    "delay_fbias": 1,
    "delay_rbias": 1,
    "die_nr": "21",
    "diode_Nr": "1,1",
    "entrance_window": "E",
    "guardring_value": "05",
    "identifier": "01E05",
    "iv_data_fbias": [
        [
            0.0,
            5.869835e-13
        ],
        [
            -0.2,
            -2.530962e-11
        ],
        [
            -0.4,
            -4.168872e-08
        ],
        [
            -0.6,
            -1.894037e-06
        ],
        [
            -0.8,
            -6.057625e-06
        ],
        [
            -1.0,
            -1.211642e-05
        ],
        [
            -1.2,
            -1.951985e-05
        ],
        [
            -1.4,
            -2.796843e-05
        ],
        [
            -1.6,
            -3.736193e-05
        ],
        [
            -1.8,
            -4.749105e-05
        ],
        [
            -2.0,
            -5.838864e-05
        ],
        [
            -2.2,
            -7.006376e-05
        ],
        [
            -2.4,
            -8.233854e-05
        ],
        [
            -2.6,
            -9.544747e-05
        ],
        [
            -2.8,
            -0.0001094844
        ],
        [
            -3.0,
            -0.0001237705
        ],
        [
            -3.2,
            -0.0001388722
        ],
        [
            -3.4,
            -0.0001542525
        ]
    ],
    "iv_data_rbias": [
        [
            0.0,
            1.133734e-13
        ],
        [
            0.5,
            1.233462e-13
        ],
        [
            1.0,
            8.32512e-14
        ],
        [
            1.5,
            1.363721e-13
        ],
        [
            2.0,
            9.688756e-14
        ],
        [
            2.5,
            1.048252e-13
        ],
        [
            3.0,
            1.553002e-13
        ],
        [
            3.5,
            5.719958e-14
        ],
        [
            4.0,
            1.154086e-13
        ],
        [
            4.5,
            8.589706e-14
        ],
        [
            5.0,
            9.586994e-14
        ],
        [
            5.5,
            1.221251e-13
        ],
        [
            6.0,
            8.32512e-14
        ],
        [
            6.5,
            1.296556e-13
        ],
        [
            7.0,
            1.601848e-13
        ],
        [
            7.5,
            1.170369e-13
        ],
        [
            8.0,
            1.876611e-13
        ],
        [
            8.5,
            1.176475e-13
        ],
        [
            9.0,
            1.158157e-13
        ],
        [
            9.5,
            1.213109e-13
        ],
        [
            10.0,
            1.453273e-13
        ],
        [
            10.5,
            1.701577e-13
        ],
        [
            11.0,
            1.239568e-13
        ],
        [
            11.5,
            1.785023e-13
        ],
        [
            12.0,
            1.726001e-13
        ],
        [
            12.5,
            1.546896e-13
        ],
        [
            13.0,
            1.75653e-13
        ],
        [
            13.5,
            1.528578e-13
        ],
        [
            14.0,
            1.563178e-13
        ],
        [
            14.5,
            1.986517e-13
        ],
        [
            15.0,
            2.035363e-13
        ],
        [
            15.5,
            2.452597e-13
        ],
        [
            16.0,
            2.214468e-13
        ],
        [
            16.5,
            2.025187e-13
        ],
        [
            17.0,
            2.316232e-13
        ],
        [
            17.5,
            2.375256e-13
        ],
        [
            18.0,
            2.055716e-13
        ],
        [
            18.5,
            2.823017e-13
        ],
        [
            19.0,
            2.442419e-13
        ],
        [
            19.5,
            3.166979e-13
        ],
        [
            20.0,
            2.511619e-13
        ],
        [
            20.5,
            3.221933e-13
        ],
        [
            21.0,
            3.596424e-13
        ],
        [
            21.5,
            2.998052e-13
        ],
        [
            22.0,
            3.806058e-13
        ],
        [
            22.5,
            3.881363e-13
        ],
        [
            23.0,
            3.834553e-13
        ],
        [
            23.5,
            4.200904e-13
        ],
        [
            24.0,
            4.436996e-13
        ],
        [
            24.5,
            4.730078e-13
        ],
        [
            25.0,
            4.662911e-13
        ],
        [
            25.5,
            4.807417e-13
        ],
        [
            26.0,
            5.063863e-13
        ],
        [
            26.5,
            5.477025e-13
        ],
        [
            27.0,
            5.877977e-13
        ],
        [
            27.5,
            6.197514e-13
        ],
        [
            28.0,
            6.148666e-13
        ],
        [
            28.5,
            6.671737e-13
        ],
        [
            29.0,
            6.818274e-13
        ],
        [
            29.5,
            7.253826e-13
        ],
        [
            30.0,
            7.84202e-13
        ],
        [
            30.5,
            8.145277e-13
        ],
        [
            31.0,
            9.040803e-13
        ],
        [
            31.5,
            9.413258e-13
        ],
        [
            32.0,
            1.004012e-12
        ],
        [
            32.5,
            1.023551e-12
        ],
        [
            33.0,
            1.074433e-12
        ],
        [
            33.5,
            1.165004e-12
        ],
        [
            34.0,
            1.253131e-12
        ],
        [
            34.5,
            1.395601e-12
        ],
        [
            35.0,
            1.421042e-12
        ],
        [
            35.5,
            1.5513e-12
        ],
        [
            36.0,
            1.728573e-12
        ],
        [
            36.5,
            1.842142e-12
        ],
        [
            37.0,
            2.03529e-12
        ],
        [
            37.5,
            2.21358e-12
        ],
        [
            38.0,
            2.414463e-12
        ],
        [
            38.5,
            2.711411e-12
        ],
        [
            39.0,
            3.012633e-12
        ],
        [
            39.5,
            3.363515e-12
        ],
        [
            40.0,
            3.785021e-12
        ],
        [
            40.5,
            4.324779e-12
        ],
        [
            41.0,
            5.050966e-12
        ],
        [
            41.5,
            6.022815e-12
        ],
        [
            42.0,
            7.29181e-12
        ],
        [
            42.5,
            9.152873e-12
        ],
        [
            43.0,
            1.260024e-11
        ],
        [
            43.5,
            1.944346e-11
        ],
        [
            44.0,
            4.654304e-11
        ],
        [
            44.5,
            4.63261e-10
        ],
        [
            45.0,
            3.426097e-08
        ],
        [
            45.5,
            3.222255e-07
        ],
        [
            46.0,
            4.849142e-06
        ],
        [
            46.5,
            1.488247e-05
        ],
        [
            47.0,
            2.759899e-05
        ],
        [
            47.5,
            6.277434e-05
        ],
        [
            48.0,
            9.359561e-05
        ],
        [
            48.5,
            0.0001189993
        ],
        [
            49.0,
            0.0001465983
        ],
        [
            49.5,
            0.0001738654
        ],
        [
            50.0,
            0.0002021598
        ]
    ],
    "row": "-2",
    "start_fbias": 0,
    "start_rbias": 0,
    "step_fbias": 0.2,
    "step_rbias": 0.5,
    "stop_fbias": -3.5,
    "stop_rbias": 50,
    "subdie_nr": "21",
    "temp_at_end": 25.0,
    "temp_at_start": 25.0,
    "time_at_end": "2025_06_13-19_17_54",
    "time_at_start": "2025_06_13-19_15_10",
    "x_pos": "0.0",
    "y_pos": "115206.94811"
}