{
    "a_diodes": 4,
    "column": "9",
    "delay_fbias": 1,
    "delay_rbias": 1,
    "die_nr": "33",
    "diode_Nr": "1,1",
    "entrance_window": "C",
    "extra": "",
    "guardring_value": "05",
    "hash": "1458172978896366550",
    "identifier": "02C05",
    "iv_data_fbias": [
        [
            0.0,
            2.796565e-13
        ],
        [
            -0.2,
            -2.89853e-11
        ],
        [
            -0.4,
            -4.308692e-08
        ],
        [
            -0.6,
            -2.253163e-06
        ],
        [
            -0.8,
            -9.152642e-06
        ],
        [
            -1.0,
            -2.503289e-05
        ],
        [
            -1.2,
            -5.700718e-05
        ],
        [
            -1.4,
            -0.0001108137
        ],
        [
            -1.6,
            -0.0001922676
        ],
        [
            -1.8,
            -0.0002766347
        ],
        [
            -2.0,
            -0.0004210725
        ],
        [
            -2.2,
            -0.0006085827
        ],
        [
            -2.4,
            -0.0008442934
        ]
    ],
    "iv_data_rbias": [
        [
            0.0,
            1.137802e-13
        ],
        [
            0.5,
            3.236856e-14
        ],
        [
            1.0,
            1.526887e-14
        ],
        [
            1.5,
            4.295209e-14
        ],
        [
            2.0,
            -1.302975e-14
        ],
        [
            2.5,
            3.379327e-14
        ],
        [
            3.0,
            7.388851e-14
        ],
        [
            3.5,
            2.035855e-14
        ],
        [
            4.0,
            -1.771225e-14
        ],
        [
            4.5,
            -1.282615e-14
        ],
        [
            5.0,
            3.88815e-14
        ],
        [
            5.5,
            2.198724e-14
        ],
        [
            6.0,
            7.002146e-14
        ],
        [
            6.5,
            6.371206e-14
        ],
        [
            7.0,
            6.004854e-14
        ],
        [
            7.5,
            4.23415e-14
        ],
        [
            8.0,
            2.91121e-14
        ],
        [
            8.5,
            5.231443e-14
        ],
        [
            9.0,
            5.943796e-14
        ],
        [
            9.5,
            6.289796e-14
        ],
        [
            10.0,
            8.650735e-14
        ],
        [
            10.5,
            8.956027e-14
        ],
        [
            11.0,
            7.124265e-14
        ],
        [
            11.5,
            5.293102e-15
        ],
        [
            12.0,
            9.566616e-14
        ],
        [
            12.5,
            9.994023e-14
        ],
        [
            13.0,
            4.763326e-14
        ],
        [
            13.5,
            3.460739e-14
        ],
        [
            14.0,
            6.595089e-14
        ],
        [
            14.5,
            8.589676e-14
        ],
        [
            15.0,
            7.836617e-14
        ],
        [
            15.5,
            6.12697e-14
        ],
        [
            16.0,
            9.302026e-14
        ],
        [
            16.5,
            4.274856e-14
        ],
        [
            17.0,
            7.816264e-14
        ],
        [
            17.5,
            4.417326e-14
        ],
        [
            18.0,
            5.35356e-14
        ],
        [
            18.5,
            3.786385e-14
        ],
        [
            19.0,
            8.976382e-14
        ],
        [
            19.5,
            9.973675e-14
        ],
        [
            20.0,
            8.711793e-14
        ],
        [
            20.5,
            4.865091e-14
        ],
        [
            21.0,
            3.786385e-14
        ],
        [
            21.5,
            1.031967e-13
        ],
        [
            22.0,
            3.135092e-14
        ],
        [
            22.5,
            7.144617e-14
        ],
        [
            23.0,
            8.080853e-14
        ],
        [
            23.5,
            9.994027e-14
        ],
        [
            24.0,
            9.159556e-14
        ],
        [
            24.5,
            7.348146e-14
        ],
        [
            25.0,
            1.219214e-13
        ],
        [
            25.5,
            1.361685e-13
        ],
        [
            26.0,
            1.408497e-13
        ],
        [
            26.5,
            1.227355e-13
        ],
        [
            27.0,
            1.178508e-13
        ],
        [
            27.5,
            9.953319e-14
        ],
        [
            28.0,
            8.956026e-14
        ],
        [
            28.5,
            1.019756e-13
        ],
        [
            29.0,
            1.237532e-13
        ],
        [
            29.5,
            9.139202e-14
        ],
        [
            30.0,
            1.746355e-13
        ],
        [
            30.5,
            1.618132e-13
        ],
        [
            31.0,
            7.409205e-14
        ],
        [
            31.5,
            1.762637e-13
        ],
        [
            32.0,
            1.81759e-13
        ],
        [
            32.5,
            2.076072e-13
        ],
        [
            33.0,
            1.664943e-13
        ],
        [
            33.5,
            1.888825e-13
        ],
        [
            34.0,
            1.640519e-13
        ],
        [
            34.5,
            1.99059e-13
        ],
        [
            35.0,
            1.561143e-13
        ],
        [
            35.5,
            2.505519e-13
        ],
        [
            36.0,
            1.760602e-13
        ],
        [
            36.5,
            2.137131e-13
        ],
        [
            37.0,
            2.027225e-13
        ],
        [
            37.5,
            2.676483e-13
        ],
        [
            38.0,
            2.515695e-13
        ],
        [
            38.5,
            2.633742e-13
        ],
        [
            39.0,
            2.924789e-13
        ],
        [
            39.5,
            2.523836e-13
        ],
        [
            40.0,
            3.32167e-13
        ],
        [
            40.5,
            3.429541e-13
        ],
        [
            41.0,
            5.277587e-13
        ],
        [
            41.5,
            1.688689e-12
        ],
        [
            42.0,
            2.787394e-11
        ],
        [
            42.5,
            3.546436e-09
        ],
        [
            43.0,
            1.631612e-05
        ],
        [
            43.5,
            1.765621e-05
        ],
        [
            44.0,
            2.563087e-05
        ],
        [
            44.5,
            5.410855e-05
        ],
        [
            45.0,
            7.847371e-05
        ],
        [
            45.5,
            9.923529e-05
        ],
        [
            46.0,
            0.0001183793
        ],
        [
            46.5,
            0.000139045
        ],
        [
            47.0,
            0.0001607426
        ],
        [
            47.5,
            0.000182311
        ],
        [
            48.0,
            0.0002044537
        ],
        [
            48.5,
            0.0002485441
        ],
        [
            49.0,
            0.0002745931
        ],
        [
            49.5,
            0.0003005484
        ],
        [
            50.0,
            0.0003265202
        ]
    ],
    "measurement_no": 1,
    "measurements_per_diode": 1,
    "row": "1",
    "start_fbias": 0,
    "start_rbias": 0,
    "step_fbias": 0.2,
    "step_rbias": 0.5,
    "stop_fbias": -2.5,
    "stop_rbias": 50,
    "subdie_nr": "15",
    "tag_1": "weiterf\u00fchrung wafertest 1",
    "tag_2": "",
    "tag_3": "",
    "temp_at_end": 25.0,
    "temp_at_start": 25.0,
    "time_at_end": "2025_06_18-07_04_20",
    "time_at_start": "2025_06_18-07_01_43",
    "x_pos": "-108005.87048",
    "y_pos": "87605.3447"
}