{
    "a_diodes": 4,
    "column": "0",
    "delay_fbias": 1,
    "delay_rbias": 1,
    "die_nr": "18",
    "diode_Nr": "1,1",
    "entrance_window": "E",
    "guardring_value": "20",
    "identifier": "02E20",
    "iv_data_fbias": [
        [
            0.0,
            3.757232e-13
        ],
        [
            -0.2,
            -3.132903e-11
        ],
        [
            -0.4,
            -4.713624e-08
        ],
        [
            -0.6,
            -1.728757e-06
        ],
        [
            -0.8,
            -5.755543e-06
        ],
        [
            -1.0,
            -1.178148e-05
        ],
        [
            -1.2,
            -1.918774e-05
        ],
        [
            -1.4,
            -2.771211e-05
        ],
        [
            -1.6,
            -3.713743e-05
        ],
        [
            -1.8,
            -4.728014e-05
        ],
        [
            -2.0,
            -5.801666e-05
        ],
        [
            -2.2,
            -6.948676e-05
        ],
        [
            -2.4,
            -8.144636e-05
        ],
        [
            -2.6,
            -9.416773e-05
        ],
        [
            -2.8,
            -0.00010739
        ],
        [
            -3.0,
            -0.0001212527
        ],
        [
            -3.2,
            -0.0001353887
        ],
        [
            -3.4,
            -0.000150128
        ]
    ],
    "iv_data_rbias": [
        [
            0.0,
            3.25727e-14
        ],
        [
            0.5,
            1.105244e-13
        ],
        [
            1.0,
            1.320986e-13
        ],
        [
            1.5,
            7.795975e-14
        ],
        [
            2.0,
            1.331162e-13
        ],
        [
            2.5,
            1.345409e-13
        ],
        [
            3.0,
            1.522479e-13
        ],
        [
            3.5,
            1.815562e-13
        ],
        [
            4.0,
            1.93768e-13
        ],
        [
            4.5,
            1.978385e-13
        ],
        [
            5.0,
            2.135103e-13
        ],
        [
            5.5,
            1.715833e-13
        ],
        [
            6.0,
            2.249079e-13
        ],
        [
            6.5,
            2.346773e-13
        ],
        [
            7.0,
            2.192092e-13
        ],
        [
            7.5,
            2.554373e-13
        ],
        [
            8.0,
            2.084221e-13
        ],
        [
            8.5,
            2.381374e-13
        ],
        [
            9.0,
            2.810821e-13
        ],
        [
            9.5,
            2.939045e-13
        ],
        [
            10.0,
            3.055055e-13
        ],
        [
            10.5,
            1.986527e-13
        ],
        [
            11.0,
            2.963467e-13
        ],
        [
            11.5,
            3.034703e-13
        ],
        [
            12.0,
            3.036738e-13
        ],
        [
            12.5,
            3.205668e-13
        ],
        [
            13.0,
            3.553702e-13
        ],
        [
            13.5,
            3.048949e-13
        ],
        [
            14.0,
            3.462115e-13
        ],
        [
            14.5,
            3.901739e-13
        ],
        [
            15.0,
            2.835243e-13
        ],
        [
            15.5,
            3.620867e-13
        ],
        [
            16.0,
            3.592374e-13
        ],
        [
            16.5,
            3.936339e-13
        ],
        [
            17.0,
            4.190749e-13
        ],
        [
            17.5,
            4.728067e-13
        ],
        [
            18.0,
            4.003503e-13
        ],
        [
            18.5,
            4.496044e-13
        ],
        [
            19.0,
            5.648019e-13
        ],
        [
            19.5,
            5.173797e-13
        ],
        [
            20.0,
            5.155479e-13
        ],
        [
            20.5,
            5.729431e-13
        ],
        [
            21.0,
            5.959419e-13
        ],
        [
            21.5,
            5.784385e-13
        ],
        [
            22.0,
            6.291173e-13
        ],
        [
            22.5,
            6.303384e-13
        ],
        [
            23.0,
            7.021843e-13
        ],
        [
            23.5,
            7.294569e-13
        ],
        [
            24.0,
            7.280324e-13
        ],
        [
            24.5,
            7.565265e-13
        ],
        [
            25.0,
            8.145326e-13
        ],
        [
            25.5,
            8.13922e-13
        ],
        [
            26.0,
            8.878033e-13
        ],
        [
            26.5,
            9.329868e-13
        ],
        [
            27.0,
            9.844796e-13
        ],
        [
            27.5,
            9.954699e-13
        ],
        [
            28.0,
            1.089094e-12
        ],
        [
            28.5,
            1.114942e-12
        ],
        [
            29.0,
            1.160532e-12
        ],
        [
            29.5,
            1.232785e-12
        ],
        [
            30.0,
            1.341674e-12
        ],
        [
            30.5,
            1.350628e-12
        ],
        [
            31.0,
            1.479666e-12
        ],
        [
            31.5,
            1.546017e-12
        ],
        [
            32.0,
            1.569626e-12
        ],
        [
            32.5,
            1.725937e-12
        ],
        [
            33.0,
            1.851311e-12
        ],
        [
            33.5,
            1.912166e-12
        ],
        [
            34.0,
            1.98849e-12
        ],
        [
            34.5,
            2.164339e-12
        ],
        [
            35.0,
            2.318005e-12
        ],
        [
            35.5,
            2.514003e-12
        ],
        [
            36.0,
            2.680083e-12
        ],
        [
            36.5,
            2.841481e-12
        ],
        [
            37.0,
            3.155528e-12
        ],
        [
            37.5,
            3.389586e-12
        ],
        [
            38.0,
            3.657023e-12
        ],
        [
            38.5,
            4.002208e-12
        ],
        [
            39.0,
            4.308724e-12
        ],
        [
            39.5,
            4.739393e-12
        ],
        [
            40.0,
            5.260631e-12
        ],
        [
            40.5,
            5.789604e-12
        ],
        [
            41.0,
            6.520274e-12
        ],
        [
            41.5,
            7.381408e-12
        ],
        [
            42.0,
            8.352242e-12
        ],
        [
            42.5,
            9.776745e-12
        ],
        [
            43.0,
            1.158612e-11
        ],
        [
            43.5,
            1.41626e-11
        ],
        [
            44.0,
            1.827369e-11
        ],
        [
            44.5,
            2.56673e-11
        ],
        [
            45.0,
            4.344071e-11
        ],
        [
            45.5,
            1.137111e-10
        ],
        [
            46.0,
            4.304488e-10
        ],
        [
            46.5,
            1.358356e-09
        ],
        [
            47.0,
            3.334055e-09
        ],
        [
            47.5,
            1.189537e-08
        ],
        [
            48.0,
            3.711414e-05
        ],
        [
            48.5,
            6.098465e-05
        ],
        [
            49.0,
            8.82033e-05
        ],
        [
            49.5,
            0.0001115897
        ],
        [
            50.0,
            0.0001373133
        ]
    ],
    "row": "1",
    "start_fbias": 0,
    "start_rbias": 0,
    "step_fbias": 0.2,
    "step_rbias": 0.5,
    "stop_fbias": -3.5,
    "stop_rbias": 50,
    "subdie_nr": "10",
    "temp_at_end": 25.0,
    "temp_at_start": 25.0,
    "time_at_end": "2025_06_12-08_58_47",
    "time_at_start": "2025_06_12-08_56_04",
    "x_pos": "-20401.06736",
    "y_pos": "86405.3447"
}