{
    "a_diodes": 16,
    "column": "-4",
    "delay_fbias": 1,
    "delay_rbias": 1,
    "die_nr": "25",
    "diode_Nr": "1,1",
    "entrance_window": "E",
    "guardring_value": "20",
    "identifier": "04E20",
    "iv_data_fbias": [
        [
            0.0,
            5.375259e-13
        ],
        [
            -0.2,
            -2.971968e-11
        ],
        [
            -0.4,
            -4.707045e-08
        ],
        [
            -0.6,
            -1.873632e-06
        ],
        [
            -0.8,
            -7.055603e-06
        ],
        [
            -1.0,
            -2.163879e-05
        ],
        [
            -1.2,
            -5.102915e-05
        ],
        [
            -1.4,
            -0.0001016305
        ],
        [
            -1.6,
            -0.0001787526
        ],
        [
            -1.8,
            -0.0002859347
        ],
        [
            -2.0,
            -0.0004306939
        ],
        [
            -2.2,
            -0.0006179636
        ],
        [
            -2.4,
            -0.0008493235
        ],
        [
            -2.6,
            -0.001126717
        ],
        [
            -2.8,
            -0.001448225
        ],
        [
            -3.0,
            -0.001824464
        ],
        [
            -3.2,
            -0.002260159
        ]
    ],
    "iv_data_rbias": [
        [
            0.0,
            3.074092e-14
        ],
        [
            0.5,
            5.414665e-14
        ],
        [
            1.0,
            2.646519e-15
        ],
        [
            1.5,
            -1.099375e-14
        ],
        [
            2.0,
            3.521854e-14
        ],
        [
            2.5,
            -3.318461e-14
        ],
        [
            3.0,
            7.205713e-14
        ],
        [
            3.5,
            3.399737e-14
        ],
        [
            4.0,
            1.872981e-14
        ],
        [
            4.5,
            1.771188e-14
        ],
        [
            5.0,
            2.544815e-14
        ],
        [
            5.5,
            4.946551e-14
        ],
        [
            6.0,
            2.91127e-14
        ],
        [
            6.5,
            4.295261e-14
        ],
        [
            7.0,
            2.707683e-14
        ],
        [
            7.5,
            -8.143548e-15
        ],
        [
            8.0,
            5.943838e-14
        ],
        [
            8.5,
            1.934057e-14
        ],
        [
            9.0,
            5.394312e-14
        ],
        [
            9.5,
            1.974774e-14
        ],
        [
            10.0,
            8.34693e-15
        ],
        [
            10.5,
            -1.974795e-14
        ],
        [
            11.0,
            -2.035952e-15
        ],
        [
            11.5,
            3.399737e-14
        ],
        [
            12.0,
            1.954415e-14
        ],
        [
            12.5,
            6.961478e-14
        ],
        [
            13.0,
            4.010321e-14
        ],
        [
            13.5,
            7.124301e-14
        ],
        [
            14.0,
            5.211137e-14
        ],
        [
            14.5,
            2.32087e-14
        ],
        [
            15.0,
            4.43773e-14
        ],
        [
            15.5,
            8.548999e-14
        ],
        [
            16.0,
            9.159583e-14
        ],
        [
            16.5,
            1.649036e-14
        ],
        [
            17.0,
            5.496077e-14
        ],
        [
            17.5,
            2.748401e-14
        ],
        [
            18.0,
            6.371248e-14
        ],
        [
            18.5,
            6.880068e-14
        ],
        [
            19.0,
            3.888204e-14
        ],
        [
            19.5,
            5.557135e-14
        ],
        [
            20.0,
            9.892286e-14
        ],
        [
            20.5,
            5.211137e-14
        ],
        [
            21.0,
            4.905845e-14
        ],
        [
            21.5,
            1.139839e-13
        ],
        [
            22.0,
            9.871932e-14
        ],
        [
            22.5,
            1.090993e-13
        ],
        [
            23.0,
            5.923486e-14
        ],
        [
            23.5,
            8.528645e-14
        ],
        [
            24.0,
            9.953343e-14
        ],
        [
            24.5,
            1.10931e-13
        ],
        [
            25.0,
            7.592418e-14
        ],
        [
            25.5,
            1.023828e-13
        ],
        [
            26.0,
            6.635835e-14
        ],
        [
            26.5,
            1.400355e-13
        ],
        [
            27.0,
            7.938412e-14
        ],
        [
            27.5,
            7.979118e-14
        ],
        [
            28.0,
            7.755237e-14
        ],
        [
            28.5,
            4.72267e-14
        ],
        [
            29.0,
            1.162227e-13
        ],
        [
            29.5,
            1.105239e-13
        ],
        [
            30.0,
            1.542825e-13
        ],
        [
            30.5,
            7.429594e-14
        ],
        [
            31.0,
            1.434955e-13
        ],
        [
            31.5,
            9.790519e-14
        ],
        [
            32.0,
            1.331156e-13
        ],
        [
            32.5,
            1.512296e-13
        ],
        [
            33.0,
            1.296556e-13
        ],
        [
            33.5,
            1.463449e-13
        ],
        [
            34.0,
            4.498789e-14
        ],
        [
            34.5,
            1.302662e-13
        ],
        [
            35.0,
            1.844046e-13
        ],
        [
            35.5,
            1.58353e-13
        ],
        [
            36.0,
            1.837941e-13
        ],
        [
            36.5,
            2.012974e-13
        ],
        [
            37.0,
            1.848117e-13
        ],
        [
            37.5,
            1.756529e-13
        ],
        [
            38.0,
            2.188009e-13
        ],
        [
            38.5,
            1.892893e-13
        ],
        [
            39.0,
            1.514331e-13
        ],
        [
            39.5,
            2.684617e-13
        ],
        [
            40.0,
            2.297914e-13
        ],
        [
            40.5,
            1.884751e-13
        ],
        [
            41.0,
            2.413926e-13
        ],
        [
            41.5,
            2.674441e-13
        ],
        [
            42.0,
            2.751782e-13
        ],
        [
            42.5,
            3.260602e-13
        ],
        [
            43.0,
            5.336587e-13
        ],
        [
            43.5,
            2.456999e-12
        ],
        [
            44.0,
            3.959721e-11
        ],
        [
            44.5,
            4.545442e-10
        ],
        [
            45.0,
            1.937675e-09
        ],
        [
            45.5,
            6.337487e-09
        ],
        [
            46.0,
            1.7717e-08
        ],
        [
            46.5,
            9.997527e-05
        ],
        [
            47.0,
            0.0001076246
        ],
        [
            47.5,
            0.0001224885
        ],
        [
            48.0,
            0.0001409502
        ],
        [
            48.5,
            0.0001598076
        ],
        [
            49.0,
            0.0001802622
        ],
        [
            49.5,
            0.0002006639
        ],
        [
            50.0,
            0.0002189075
        ]
    ],
    "row": "-4",
    "start_fbias": 0,
    "start_rbias": 0,
    "step_fbias": 0.2,
    "step_rbias": 0.5,
    "stop_fbias": -3.5,
    "stop_rbias": 50,
    "subdie_nr": "2",
    "temp_at_end": 25.0,
    "temp_at_start": 25.0,
    "time_at_end": "2025_06_14-23_37_59",
    "time_at_start": "2025_06_14-23_35_14",
    "x_pos": "18001.06736",
    "y_pos": "126008.01705"
}