{
    "a_diodes": 1,
    "column": "-4",
    "delay_fbias": 1,
    "delay_rbias": 1,
    "die_nr": "7",
    "diode_Nr": "1,1",
    "entrance_window": "E",
    "extra": "wholewafer2",
    "guardring_value": "20",
    "hash": "-8685861046459469735",
    "identifier": "01E20",
    "iv_data_fbias": [
        [
            0.0,
            6.350117e-13
        ],
        [
            -0.2,
            -3.178772e-11
        ],
        [
            -0.4,
            -5.363575e-08
        ],
        [
            -0.6,
            -5.045227e-06
        ],
        [
            -0.8,
            -1.870956e-05
        ],
        [
            -1.0,
            -4.761629e-05
        ],
        [
            -1.2,
            -9.810985e-05
        ],
        [
            -1.4,
            -0.0001794445
        ],
        [
            -1.6,
            -0.0003063624
        ],
        [
            -1.8,
            -0.0004780678
        ],
        [
            -2.0,
            -0.0007097998
        ],
        [
            -2.2,
            -0.001006022
        ],
        [
            -2.4,
            -0.001367936
        ]
    ],
    "iv_data_rbias": [
        [
            0.0,
            -1.506525e-14
        ],
        [
            0.5,
            -1.628482e-15
        ],
        [
            1.0,
            5.41388e-14
        ],
        [
            1.5,
            6.370468e-14
        ],
        [
            2.0,
            9.464118e-14
        ],
        [
            2.5,
            1.585494e-13
        ],
        [
            3.0,
            6.472236e-14
        ],
        [
            3.5,
            1.723894e-13
        ],
        [
            4.0,
            1.420636e-13
        ],
        [
            4.5,
            1.599741e-13
        ],
        [
            5.0,
            1.644517e-13
        ],
        [
            5.5,
            1.679118e-13
        ],
        [
            6.0,
            2.291742e-13
        ],
        [
            6.5,
            2.061753e-13
        ],
        [
            7.0,
            1.544789e-13
        ],
        [
            7.5,
            2.324305e-13
        ],
        [
            8.0,
            1.8684e-13
        ],
        [
            8.5,
            1.666906e-13
        ],
        [
            9.0,
            2.118741e-13
        ],
        [
            9.5,
            1.988482e-13
        ],
        [
            10.0,
            2.236788e-13
        ],
        [
            10.5,
            2.108565e-13
        ],
        [
            11.0,
            2.342623e-13
        ],
        [
            11.5,
            2.147235e-13
        ],
        [
            12.0,
            2.995953e-13
        ],
        [
            12.5,
            2.6296e-13
        ],
        [
            13.0,
            2.5258e-13
        ],
        [
            13.5,
            2.234753e-13
        ],
        [
            14.0,
            3.287e-13
        ],
        [
            14.5,
            3.085506e-13
        ],
        [
            15.0,
            2.786318e-13
        ],
        [
            15.5,
            2.989847e-13
        ],
        [
            16.0,
            3.114e-13
        ],
        [
            16.5,
            3.645212e-13
        ],
        [
            17.0,
            3.223906e-13
        ],
        [
            17.5,
            3.168954e-13
        ],
        [
            18.0,
            3.582118e-13
        ],
        [
            18.5,
            4.316857e-13
        ],
        [
            19.0,
            4.103153e-13
        ],
        [
            19.5,
            4.208987e-13
        ],
        [
            20.0,
            4.955942e-13
        ],
        [
            20.5,
            4.754447e-13
        ],
        [
            21.0,
            4.5326e-13
        ],
        [
            21.5,
            4.976293e-13
        ],
        [
            22.0,
            5.222563e-13
        ],
        [
            22.5,
            5.389457e-13
        ],
        [
            23.0,
            5.723247e-13
        ],
        [
            23.5,
            5.613342e-13
        ],
        [
            24.0,
            6.517011e-13
        ],
        [
            24.5,
            6.08553e-13
        ],
        [
            25.0,
            6.730717e-13
        ],
        [
            25.5,
            7.465461e-13
        ],
        [
            26.0,
            6.863011e-13
        ],
        [
            26.5,
            7.858271e-13
        ],
        [
            27.0,
            8.391517e-13
        ],
        [
            27.5,
            8.615397e-13
        ],
        [
            28.0,
            8.843353e-13
        ],
        [
            28.5,
            9.484471e-13
        ],
        [
            29.0,
            1.025788e-12
        ],
        [
            29.5,
            1.11066e-12
        ],
        [
            30.0,
            1.136305e-12
        ],
        [
            30.5,
            1.233999e-12
        ],
        [
            31.0,
            1.212018e-12
        ],
        [
            31.5,
            1.29058e-12
        ],
        [
            32.0,
            1.396822e-12
        ],
        [
            32.5,
            1.486579e-12
        ],
        [
            33.0,
            1.59852e-12
        ],
        [
            33.5,
            1.708222e-12
        ],
        [
            34.0,
            1.808969e-12
        ],
        [
            34.5,
            1.882443e-12
        ],
        [
            35.0,
            1.991332e-12
        ],
        [
            35.5,
            2.219487e-12
        ],
        [
            36.0,
            2.326545e-12
        ],
        [
            36.5,
            2.460059e-12
        ],
        [
            37.0,
            2.697172e-12
        ],
        [
            37.5,
            2.956468e-12
        ],
        [
            38.0,
            3.222888e-12
        ],
        [
            38.5,
            3.544057e-12
        ],
        [
            39.0,
            3.839581e-12
        ],
        [
            39.5,
            4.227304e-12
        ],
        [
            40.0,
            4.647796e-12
        ],
        [
            40.5,
            5.164558e-12
        ],
        [
            41.0,
            5.843328e-12
        ],
        [
            41.5,
            6.613688e-12
        ],
        [
            42.0,
            7.725977e-12
        ],
        [
            42.5,
            8.931684e-12
        ],
        [
            43.0,
            1.073292e-11
        ],
        [
            43.5,
            1.323348e-11
        ],
        [
            44.0,
            1.706024e-11
        ],
        [
            44.5,
            2.363241e-11
        ],
        [
            45.0,
            3.979913e-11
        ],
        [
            45.5,
            1.218915e-10
        ],
        [
            46.0,
            1.94247e-09
        ],
        [
            46.5,
            4.755208e-07
        ],
        [
            47.0,
            8.262673e-06
        ],
        [
            47.5,
            2.029255e-05
        ],
        [
            48.0,
            5.235293e-05
        ],
        [
            48.5,
            8.843086e-05
        ],
        [
            49.0,
            0.0001154994
        ],
        [
            49.5,
            0.0001417711
        ],
        [
            50.0,
            0.000168618
        ]
    ],
    "measurement_no": 3,
    "measurements_per_diode": 4,
    "row": "10",
    "start_fbias": 0,
    "start_rbias": 0,
    "step_fbias": 0.2,
    "step_rbias": 0.5,
    "stop_fbias": -2.5,
    "stop_rbias": 50,
    "subdie_nr": "18",
    "tag_1": "whole wafer",
    "tag_2": "run_2",
    "tag_3": "",
    "temp_at_end": 25.0,
    "temp_at_start": 25.0,
    "time_at_end": "2025_06_23-12_56_11",
    "time_at_start": "2025_06_23-12_53_29",
    "x_pos": "18001.06736",
    "y_pos": "13200.53447"
}